claude_config_manager.py
gemini_mcp_client.py
llm_client.py
mcp_cli_client.py
mcp_server.py
mcp_stdio_wrapper.py
nl_to_sql.py
oauth_callback_config.py
oauth_client.py
schema_introspector.py
semantic_catalog.py
semantic_models.py
simple_sql_executor.py
sql_executor.py
sql_validator.py
user_api_client.py
oauth/README.md
oauth/__init__.py
oauth/client.py
oauth/decorators.py
oauth/middleware.py
oauth/__pycache__/__init__.cpython-312.pyc
oauth/__pycache__/__init__.cpython-313.pyc
oauth/__pycache__/client.cpython-312.pyc
oauth/__pycache__/client.cpython-313.pyc
oauth/__pycache__/middleware.cpython-312.pyc
oauth/__pycache__/middleware.cpython-313.pyc
plugins/README.md
plugins/__init__.py
plugins/base.py
plugins/registry.py
plugins/__pycache__/__init__.cpython-312.pyc
plugins/__pycache__/__init__.cpython-313.pyc
plugins/__pycache__/base.cpython-312.pyc
plugins/__pycache__/base.cpython-313.pyc
plugins/__pycache__/registry.cpython-312.pyc
plugins/__pycache__/registry.cpython-313.pyc
plugins/protheus/README.md
plugins/protheus/__init__.py
plugins/protheus/cache.py
plugins/protheus/dictionary.py
plugins/protheus/generator.py
plugins/protheus/inferencer.py
plugins/protheus/protheus_mapper.py
plugins/protheus/__pycache__/__init__.cpython-312.pyc
plugins/protheus/__pycache__/__init__.cpython-313.pyc
plugins/protheus/__pycache__/cache.cpython-312.pyc
plugins/protheus/__pycache__/cache.cpython-313.pyc
plugins/protheus/__pycache__/dictionary.cpython-312.pyc
plugins/protheus/__pycache__/dictionary.cpython-313.pyc
plugins/protheus/__pycache__/generator.cpython-312.pyc
plugins/protheus/__pycache__/generator.cpython-313.pyc
plugins/protheus/__pycache__/inferencer.cpython-312.pyc
plugins/protheus/__pycache__/inferencer.cpython-313.pyc
plugins/protheus/__pycache__/protheus_mapper.cpython-312.pyc
plugins/protheus/__pycache__/protheus_mapper.cpython-313.pyc
simpliq_mcp_server_dev_test-0.1.1.dist-info/METADATA
simpliq_mcp_server_dev_test-0.1.1.dist-info/WHEEL
simpliq_mcp_server_dev_test-0.1.1.dist-info/entry_points.txt
simpliq_mcp_server_dev_test-0.1.1.dist-info/top_level.txt
simpliq_mcp_server_dev_test-0.1.1.dist-info/RECORD
