Metadata-Version: 2.4
Name: simpliq-mcp-server-dev-test
Version: 0.1.1
Summary: Simpliq Data Proxy MCP Server
Author: Gerson Freire
Classifier: Programming Language :: Python :: 3
Classifier: License :: OSI Approved :: MIT License
Classifier: Operating System :: OS Independent
Requires-Python: >=3.9
Requires-Dist: flask>=2.0
Requires-Dist: sqlalchemy>=1.4
Requires-Dist: pyyaml>=6.0
Requires-Dist: requests>=2.28
Requires-Dist: pyodbc>=4.0.0
Requires-Dist: httpx>=0.25.0
Requires-Dist: cachetools>=5.3.0
Requires-Dist: sqlparse>=0.4.4
Requires-Dist: sqlglot>=20.0.0
Requires-Dist: fuzzywuzzy>=0.18.0
Requires-Dist: python-Levenshtein>=0.12.2
Requires-Dist: pydantic>=2.0.0
Requires-Dist: google-generativeai
Requires-Dist: flask-cors
